{
  "schema_version": "1.0.0",
  "task_id": "completion-verify",
  "created_at": "2026-04-06T23:55:44.273Z",
  "entries": [
    {
      "task_id": "completion-verify",
      "type": "completion_verify",
      "timestamp": "2026-04-06T23:55:44.273Z",
      "agent": "completion_verify",
      "verdict": "pass",
      "summary": "All 1 completed task(s) skipped — research/inventory tasks",
      "phase": 5,
      "tasks_checked": 1,
      "tasks_skipped": 1,
      "tasks_blocked": 0,
      "blocked_tasks": []
    }
  ]
}